usito/__init__.py
usito/data/__init__.py
usito/data/load.py
usito/data/save.py
usito/data/zip.py
usito/data/utils/__init__.py
usito/data/utils/engine.py
usito/data/utils/image.py
usito/data/utils/np.py
usito/data/utils/table.py
usito/data/utils/zip/__init__.py
usito/data/utils/zip/unzip.py
usito/data/utils/zip/utils.py
usito/data/utils/zip/zip.py
usito-0.0.2.dist-info/LICENSE
usito-0.0.2.dist-info/METADATA
usito-0.0.2.dist-info/WHEEL
usito-0.0.2.dist-info/top_level.txt
usito-0.0.2.dist-info/RECORD
