Metadata-Version: 2.1
Name: usito
Version: 0.0.2
Summary: A Package for Neural Networks for Beginners and Professionals
Home-page: https://github.tik.uni-stuttgart.de/AliB/usito
Author: Alexander Birk & Felix Fischer
Author-email: felix.fischer@ito.uni-stuttgart.de
License: GNU Lesser General Public License v3 or later (LGPLv3+)
Project-URL: ITO Homepage, https://www.ito.uni-stuttgart.de/
Project-URL: Bug Tracker, https://github.tik.uni-stuttgart.de/AliB/usito/issues
Keywords: neural networks,students,research
Platform: UNKNOWN
Classifier: Intended Audience :: Developers
Classifier: Development Status :: 5 - Production/Stable
Classifier: Programming Language :: Python :: 3
Classifier: License :: OSI Approved :: GNU Lesser General Public License v3 or later (LGPLv3+)
Classifier: Operating System :: OS Independent
Requires-Python: >=3.0
License-File: LICENSE
Requires-Dist: numpy
Requires-Dist: Pandas
Requires-Dist: Pillow
Requires-Dist: XlsxWriter
Requires-Dist: h5py
